{
  "gitSyncId": "6a1b16bf9b1e98311441a58d_1b18f4c2-93fb-4523-86a2-ee576cedb77d",
  "id": "Cadastro_den_Geral_Query_Salvar_Geral",
  "pluginId": "postgres-plugin",
  "pluginType": "DB",
  "unpublishedAction": {
    "actionConfiguration": {
      "body": "INSERT INTO public.\"Cadastro_Geral\" (\n    \"Num_Denuncia_Geral\",\n    \"data_e_hora_denuncia_Geral\",\n    \"Data_Reg_Geral\", \n    \"Hora_Reg_Geral\",\n    \"Nome_Denunciante_Geral\",\n    \"Nome_Agressor_Geral\",\n    \"Nome_Testemunha_Geral\",\n    \"Localizacao_Geral\",\n    \"Resposta_Denunciante_Geral\",\n    \"Descricao_Geral\",\n    \"telefone_Geral\",\n    \"email_Geral\",\n    \"Classificacao_Geral\",\n    \"Foto_URL_Geral\",\n    \"dia_cadastro_Geral\",      \n    \"mes_cadastro_Geral\",       \n    \"dia_denuncia_Geral\",     \n    \"mes_denuncia_Geral\",\n    \"situacao_Geral\" \n) VALUES (\n    {{ n_denuncia_Geral.text ? Number(n_denuncia_Geral.text) : null }},\n    {{ data_e_hora_denuncia.selectedDate ? \"'\" + moment(data_e_hora_denuncia.selectedDate).format(\"DD/MM/YYYY\") + \" às \" + moment(data_e_hora_denuncia.selectedDate).format(\"HH\") + \":\" + moment(data_e_hora_denuncia.selectedDate).format(\"mm\") + \"'\" : null }},\n    {{ Data_Reg_Geral.text ? \"'\" + Data_Reg_Geral.text + \"'\" : null }},\n    {{ Hora_Reg_Geral.text ? \"'\" + Hora_Reg_Geral.text + \"'\" : null }},\n    {{ Denunciante_Geral.text ? \"'\" + Denunciante_Geral.text + \"'\" : null }},\n    {{ Agressor_Geral.text ? \"'\" + Agressor_Geral.text + \"'\" : null }},\n    {{ Testemunha_Geral.text ? \"'\" + Testemunha_Geral.text + \"'\" : null }},\n    {{ Select_cidade.selectedOptionValue ? \"'\" + Select_cidade.selectedOptionValue + \"'\" : \"''\" }},\n    {{ Resposta_Denunciante.selectedOptionValue ? \"'\" + Resposta_Denunciante.selectedOptionValue + \"'\" : \"'SIM'\" }},\n    {{ Text_den_Geral.text ? \"'\" + Text_den_Geral.text.replace(/<\\/?[^>]+(>|$)/g, \"\").replace(/&ccedil;/g, \"ç\").replace(/&atilde;/g, \"ã\").replace(/&otilde;/g, \"õ\").replace(/&éacute;/g, \"é\").replace(/&aacute;/g, \"á\").replace(/&iacute;/g, \"í\").replace(/&ó;/g, \"ó\").replace(/&uacute;/g, \"ú\").replace(/&Acirc;/g, \"Â\").replace(/&ecirc;/g, \"ê\").replace(/&nbsp;/g, \" \") + \"'\" : null }},\n    {{ telefone_Geral.text ? \"'\" + telefone_Geral.text + \"'\" : null }},\n    {{ email_Geral.text ? \"'\" + email_Geral.text + \"'\" : null }},\n    {{ classif_denun.selectedOptionValue ? \"'\" + classif_denun.selectedOptionValue + \"'\" : null }},\n    {{ appsmith.store.urlsParaOBanco ? \"'\" + appsmith.store.urlsParaOBanco + \"'\" : null }},\n    {{ Data_Reg_Geral.text ? moment(Data_Reg_Geral.text, 'DD/MM/YYYY').date() : null }},\n    {{ Data_Reg_Geral.text ? \"'\" + [\"Janeiro\", \"Fevereiro\", \"Março\", \"Abril\", \"Maio\", \"Junho\", \"Julho\", \"Agosto\", \"Setembro\", \"Outubro\", \"Novembro\", \"Dezembro\"][moment(Data_Reg_Geral.text, 'DD/MM/YYYY').month()] + \"'\" : null }},\n    {{ data_e_hora_denuncia.selectedDate ? moment(data_e_hora_denuncia.selectedDate).date() : null }},\n    {{ data_e_hora_denuncia.selectedDate ? \"'\" + [\"Janeiro\", \"Fevereiro\", \"Março\", \"Abril\", \"Maio\", \"Junho\", \"Julho\", \"Agosto\", \"Setembro\", \"Outubro\", \"Novembro\", \"Dezembro\"][moment(data_e_hora_denuncia.selectedDate).month()] + \"'\" : null }},\n    'Encaminhada'\n);\n",
      "encodeParamsToggle": true,
      "paginationType": "NONE",
      "pluginSpecifiedTemplates": [
        {
          "value": false
        }
      ],
      "timeoutInMillisecond": 10000
    },
    "confirmBeforeExecute": false,
    "datasource": {
      "id": "BD_Supabase",
      "isAutoGenerated": false,
      "name": "BD_Supabase",
      "pluginId": "postgres-plugin"
    },
    "dynamicBindingPathList": [
      {
        "key": "body"
      }
    ],
    "name": "Query_Salvar_Geral",
    "pageId": "Cadastro_den_Geral",
    "runBehaviour": "MANUAL",
    "userSetOnLoad": false
  }
}