{
  "gitSyncId": "6a1b16bf9b1e98311441a58d_e7dbeafb-7b3d-4e67-81ea-1a9f256f9546",
  "id": "Dashboard_JSObject1.formatarEnvenenamento",
  "pluginId": "js-plugin",
  "pluginType": "JS",
  "unpublishedAction": {
    "actionConfiguration": {
      "encodeParamsToggle": true,
      "jsArguments": [],
      "paginationType": "NONE",
      "timeoutInMillisecond": 10000
    },
    "collectionId": "Dashboard_JSObject1",
    "confirmBeforeExecute": false,
    "datasource": {
      "isAutoGenerated": false,
      "name": "UNUSED_DATASOURCE",
      "pluginId": "js-plugin"
    },
    "dynamicBindingPathList": [
      {
        "key": "body"
      }
    ],
    "fullyQualifiedName": "JSObject1.formatarEnvenenamento",
    "name": "formatarEnvenenamento",
    "pageId": "Dashboard",
    "runBehaviour": "MANUAL",
    "userSetOnLoad": false
  }
}